GiftReaper/__init__.py
GiftReaper/utils.py
GiftReaper/voucher.py
GiftReaper-0.0.2.dist-info/LICENSE.txt
GiftReaper-0.0.2.dist-info/METADATA
GiftReaper-0.0.2.dist-info/WHEEL
GiftReaper-0.0.2.dist-info/top_level.txt
GiftReaper-0.0.2.dist-info/RECORD
