Metadata-Version: 2.2
Name: GiftReaper
Version: 0.0.2
Summary: GiftReaper เป็นแพ็กเกจสำหรับช่วยในการทำธุรกรรมจากการส่งซองทรูมันนี่
Author-email: NatchaLatte Official <foxteary@gmail.com>
Project-URL: Homepage, https://github.com/NatchaLatte/GiftReaper
Project-URL: Issues, https://github.com/NatchaLatte/GiftReaper/issues
Keywords: giftreaper,truemoney,angpao,payment,red envelope
Classifier: Programming Language :: Python :: 3
Classifier: License :: OSI Approved :: MIT License
Classifier: Operating System :: OS Independent
Requires-Python: >=3.8
License-File: LICENSE.txt
Requires-Dist: cloudscraper==1.2.71
